[
  {
    "name": "Trends of the season"
  },
  {
    "name": "Blouses and shirts"
  },
  {
    "name": "Body"
  },
  {
    "name": "Pants"
  },
  {
    "name": "Outerwear"
  },
  {
    "name": "Sweaters and cardigans"
  },
  {
    "name": "Jeans"
  },
  {
    "name": "Indoor clothing"
  },
  {
    "name": "Overalls"
  },
  {
    "name": "Swimwear and Beachwear"
  },
  {
    "name": "Underwear"
  },
  {
    "name": "Socks, stockings and tights"
  },
  {
    "name": "Jackets and suits"
  },
  {
    "name": "Dresses"
  },
  {
    "name": "Tracksuits"
  },
  {
    "name": "Hoodies and sweatshirts"
  },
  {
    "name": "Tops and T-shirts"
  },
  {
    "name": "Tunics"
  },
  {
    "name": "T-Shirts & Polo"
  },
  {
    "name": "Shorts"
  },
  {
    "name": "Skirts"
  },
  {
    "name": "Large size clothing"
  },
  {
    "name": "Clothes for pregnant women"
  }
]
